LICENSE
MANIFEST.in
README.rst
requirements.txt
setup.py
sqs_s3_logger/__init__.py
sqs_s3_logger/environment.py
sqs_s3_logger/lambda_function.py
sqs_s3_logger/lambda_function_builder.py
sqs_s3_logger/main.py
sqs_s3_logger/tests.py
sqs_s3_logger/version.py
sqs_s3_logger.egg-info/PKG-INFO
sqs_s3_logger.egg-info/SOURCES.txt
sqs_s3_logger.egg-info/dependency_links.txt
sqs_s3_logger.egg-info/entry_points.txt
sqs_s3_logger.egg-info/requires.txt
sqs_s3_logger.egg-info/top_level.txt