Metadata-Version: 1.0
Name: sqs-s3-logger
Version: 1.0.6
Summary: Automated serverless logging to S3 via SQS.
Home-page: https://github.com/ellimilial/sqs-s3-logger
Author: Mateusz Kaczyński
Author-email: contact@ellimilial.com
License: UNKNOWN
Keywords: logging sqs s3 archive storage
Platform: UNKNOWN
